{
  "project_info": {
    "project_number": "972650655088",
    "project_id": "thesocial-62d49",
    "storage_bucket": "thesocial-62d49.appspot.com"
  },
  "client": [
    {
      "client_info": {
        "mobilesdk_app_id": "1:972650655088:android:1d9a5dd8ad5f2317f133b5",
        "android_client_info": {
          "package_name": "com.example.smesterproject"
        }
      },
      "oauth_client": [
        {
          "client_id": "972650655088-eiivdojrqj303ds3mnivo9armg1qvd1a.apps.googleusercontent.com",
          "client_type": 1,
          "android_info": {
            "package_name": "com.example.smesterproject",
            "certificate_hash": "eb859b68bba310125a110e60bc3cf8cd7ccdc418"
          }
        },
        {
          "client_id": "972650655088-h99snpd4vh2je2umor54ho5shemujfpr.apps.googleusercontent.com",
          "client_type": 3
        }
      ],
      "api_key": [
        {
          "current_key": "AIzaSyCy-TsNY1Wj27YrUGYxxTU8dkWFiCepWxc"
        }
      ],
      "services": {
        "appinvite_service": {
          "other_platform_oauth_client": [
            {
              "client_id": "972650655088-h99snpd4vh2je2umor54ho5shemujfpr.apps.googleusercontent.com",
              "client_type": 3
            },
            {
              "client_id": "972650655088-ootcndji4ha56ntpluda9pre44aiocko.apps.googleusercontent.com",
              "client_type": 2,
              "ios_info": {
                "bundle_id": "com.example.smesterproject"
              }
            }
          ]
        }
      }
    }
  ],
  "configuration_version": "1"
}